bitwarden_workflow_linter/__about__.py
bitwarden_workflow_linter/__init__.py
bitwarden_workflow_linter/actionlint_version.yaml
bitwarden_workflow_linter/actions.py
bitwarden_workflow_linter/cli.py
bitwarden_workflow_linter/default_actions.json
bitwarden_workflow_linter/default_settings.yaml
bitwarden_workflow_linter/lint.py
bitwarden_workflow_linter/load.py
bitwarden_workflow_linter/rule.py
bitwarden_workflow_linter/utils.py
bitwarden_workflow_linter/zizmor_version.yaml
bitwarden_workflow_linter/models/__init__.py
bitwarden_workflow_linter/models/job.py
bitwarden_workflow_linter/models/step.py
bitwarden_workflow_linter/models/workflow.py
bitwarden_workflow_linter/rules/__init__.py
bitwarden_workflow_linter/rules/check_blocked_domains.py
bitwarden_workflow_linter/rules/check_pr_target.py
bitwarden_workflow_linter/rules/job_environment_prefix.py
bitwarden_workflow_linter/rules/name_capitalized.py
bitwarden_workflow_linter/rules/name_exists.py
bitwarden_workflow_linter/rules/permissions_exist.py
bitwarden_workflow_linter/rules/pinned_job_runner.py
bitwarden_workflow_linter/rules/run_actionlint.py
bitwarden_workflow_linter/rules/run_zizmor.py
bitwarden_workflow_linter/rules/step_approved.py
bitwarden_workflow_linter/rules/step_pinned.py
bitwarden_workflow_linter/rules/underscore_outputs.py
bitwarden_workflow_linter-3.3.1.dist-info/METADATA
bitwarden_workflow_linter-3.3.1.dist-info/WHEEL
bitwarden_workflow_linter-3.3.1.dist-info/entry_points.txt
bitwarden_workflow_linter-3.3.1.dist-info/licenses/LICENSE.txt
bitwarden_workflow_linter-3.3.1.dist-info/RECORD
