Metadata-Version: 2.4
Name: bitwarden_workflow_linter
Version: 3.3.1
Summary: Custom GitHub Action Workflow Linter
Project-URL: Homepage, https://github.com/bitwarden/workflow-linter
Project-URL: Issues, https://github.com/bitwarden/workflow-linter/issues
License-File: LICENSE.txt
Classifier: License :: OSI Approved :: GNU General Public License v3 (GPLv3)
Classifier: Operating System :: OS Independent
Classifier: Programming Language :: Python :: 3
Requires-Python: >=3.11
Requires-Dist: annotated-types==0.7.0
Requires-Dist: dataclasses-json==0.6.6
Requires-Dist: marshmallow==3.21.2
Requires-Dist: mypy-extensions==1.0.0
Requires-Dist: packaging==24.0
Requires-Dist: pydantic-core==2.20.1
Requires-Dist: pydantic==2.8.1
Requires-Dist: pyyaml==6.0.1
Requires-Dist: ruamel-yaml-clib==0.2.12
Requires-Dist: ruamel-yaml==0.18.6
Requires-Dist: typing-extensions==4.12.2
Requires-Dist: typing-inspect==0.9.0
Requires-Dist: urllib3==2.2.1
